{"data":{"site":{"siteMetadata":{"title":"Micro Binfie Virtual Conference 2020","subtitle":"An online seminar series chaired by the Micro Binfie Podcast","copyright":"© All rights reserved.","menu":[{"label":"Sessions","path":"/conference2020/"},{"label":"About","path":"/conference2020/about/"},{"label":"Register to attend","path":"/conference2020/register/"}],"author":{"name":"Micro Binfie Virtual Conference 2020","email":"microbinfie@gmail.com","rss":"#"}}},"allMarkdownRemark":{"group":[{"fieldValue":"Bioinformatics software and protocols","totalCount":1},{"fieldValue":"Gatsby","totalCount":1},{"fieldValue":"Helvetica","totalCount":1},{"fieldValue":"History of typography","totalCount":1},{"fieldValue":"Linotype","totalCount":1},{"fieldValue":"Monotype","totalCount":1},{"fieldValue":"Open source","totalCount":1},{"fieldValue":"Population genetics and Microbial epidemiology","totalCount":1},{"fieldValue":"Typography","totalCount":1}]}},"pageContext":{}}